Metadata-Version: 1.0
Name: Jiyatesting
Version: 0.1
Summary: Gaussian and Binomial distributions
Home-page: UNKNOWN
Author: Jiya
Author-email: UNKNOWN
License: UNKNOWN
Platform: UNKNOWN
